libcrap/__init__.py
libcrap/core.py
libcrap/torch.py
libcrap/visualization.py
libcrap/torch/__init__.py
libcrap/torch/click.py
libcrap/torch/general_purpose.py
libcrap/torch/training.py
libcrap-0.3.1.dist-info/LICENSE
libcrap-0.3.1.dist-info/METADATA
libcrap-0.3.1.dist-info/WHEEL
libcrap-0.3.1.dist-info/top_level.txt
libcrap-0.3.1.dist-info/RECORD
